mcp_server_did_jis/__init__.py
mcp_server_did_jis/server.py
mcp_server_did_jis-1.0.0.dist-info/METADATA
mcp_server_did_jis-1.0.0.dist-info/WHEEL
mcp_server_did_jis-1.0.0.dist-info/entry_points.txt
mcp_server_did_jis-1.0.0.dist-info/licenses/LICENSE
mcp_server_did_jis-1.0.0.dist-info/RECORD
