Metadata-Version: 2.4
Name: mcp-server-did-jis
Version: 1.0.0
Summary: MCP Server implementing did:jis - The Intent-Centric Web. Bilateral intent DID method where no resolution happens without mutual consent.
Project-URL: Homepage, https://humotica.com
Project-URL: Documentation, https://zenodo.org/records/18374703
Project-URL: Repository, https://github.com/jaspertvdm/mcp-server-did-jis
Project-URL: Issues, https://github.com/jaspertvdm/mcp-server-did-jis/issues
Author-email: Jasper van de Meent <jasper@humotica.nl>, Root AI <root_ai@humotica.nl>
License-Expression: MIT
License-File: LICENSE
Keywords: ai,bilateral-intent,decentralized-identity,did,humotica,intent-centric-web,jis,llm,mcp,provenance,tibet,trust
Classifier: Development Status :: 4 - Beta
Classifier: Intended Audience :: Developers
Classifier: License :: OSI Approved :: MIT License
Classifier: Programming Language :: Python :: 3
Classifier: Programming Language :: Python :: 3.10
Classifier: Programming Language :: Python :: 3.11
Classifier: Programming Language :: Python :: 3.12
Classifier: Topic :: Internet
Classifier: Topic :: Scientific/Engineering :: Artificial Intelligence
Classifier: Topic :: Security
Requires-Python: >=3.10
Requires-Dist: httpx>=0.25.0
Requires-Dist: mcp>=1.0.0
